uo_puddles/CustomTukeyTransformer_unittest.py
uo_puddles/__init__.py
uo_puddles/cis423.py
uo_puddles/good_ai.py
uo_puddles/good_ai_22.py
uo_puddles/gremcat_df.py
uo_puddles/gremcat_oo.py
uo_puddles/mlops.py
uo_puddles-25.5.14.16.36.dist-info/licenses/LICENSE.txt
uo_puddles-25.5.14.16.36.dist-info/METADATA
uo_puddles-25.5.14.16.36.dist-info/WHEEL
uo_puddles-25.5.14.16.36.dist-info/top_level.txt
uo_puddles-25.5.14.16.36.dist-info/RECORD
